CHANGELOG.rst
LICENSE
README.rst
django_rest_tsg/__init__.py
django_rest_tsg/apps.py
django_rest_tsg/build.py
django_rest_tsg/management/__init__.py
django_rest_tsg/management/commands/__init__.py
django_rest_tsg/management/commands/buildtypescript.py
django_rest_tsg/py.typed
django_rest_tsg/templates.py
django_rest_tsg/typescript.py
django_rest_tsg-0.1.10.dist-info/LICENSE
django_rest_tsg-0.1.10.dist-info/METADATA
django_rest_tsg-0.1.10.dist-info/WHEEL
django_rest_tsg-0.1.10.dist-info/RECORD
