Metadata-Version: 2.1
Name: django-rest-tsg
Version: 0.1.10
Summary: A typescript code generator for Django Rest Framework.
Home-page: https://github.com/jinkanhq/django-rest-tsg
License: MIT
Author: Yinian Chin
Author-email: yinian@jinkan.org
Requires-Python: >=3.9.0,<4.0.0
Classifier: Development Status :: 4 - Beta
Classifier: Environment :: Web Environment
Classifier: Framework :: Django
Classifier: Framework :: Django :: 3.0
Classifier: Framework :: Django :: 3.1
Classifier: Framework :: Django :: 3.2
Classifier: Framework :: Django :: 4.0
Classifier: Framework :: Django :: 4.1
Classifier: Framework :: Django :: 4.2
Classifier: Framework :: Django :: 5.0
Classifier: Intended Audience :: Developers
Classifier: License :: OSI Approved :: MIT License
Classifier: Operating System :: OS Independent
Classifier: Programming Language :: Python
Classifier: Programming Language :: Python :: 3
Classifier: Programming Language :: Python :: 3.9
Classifier: Programming Language :: Python :: 3.10
Classifier: Programming Language :: Python :: 3.11
Classifier: Programming Language :: Python :: 3.12
Classifier: Topic :: Internet :: WWW/HTTP
Classifier: Topic :: Software Development :: Code Generators
Classifier: Topic :: Software Development :: Libraries :: Python Modules
Classifier: Typing :: Typed
Requires-Dist: django (>=3.0,<5.0) ; python_full_version >= "3.9.0" and python_version < "3.10"
Requires-Dist: django (>=3.0,<6.0) ; python_full_version >= "3.10.0" and python_full_version < "4.0.0"
Requires-Dist: djangorestframework (>=3.13,<4.0)
Requires-Dist: djangorestframework-dataclasses (>=1.3.0,<2.0.0)
Requires-Dist: inflection (>=0.5.1,<0.6.0)
Project-URL: Repository, https://github.com/jinkanhq/django-rest-tsg
